dual_audio/__init__.py
dual_audio/config.py
dual_audio/converter.py
dual_audio/helpers.py
dual_audio/loader.py
dual_audio/main.py
dual_audio/m3u/__init__.py
dual_audio/m3u/parser.py
dual_audio/m3u/writer.py
dual_audio-1.1.dist-info/METADATA
dual_audio-1.1.dist-info/WHEEL
dual_audio-1.1.dist-info/entry_points.txt
dual_audio-1.1.dist-info/top_level.txt
dual_audio-1.1.dist-info/RECORD
