Metadata-Version: 2.1
Name: dual-audio
Version: 1.1
Summary: Make videos with double audio
Home-page: https://github.com/istudyatuni/dual-audio
Author: Ilia
Author-email: istudyatuni@gmail.com
License: UNKNOWN
Keywords: video movie audio dual-audio
Platform: UNKNOWN
Classifier: Programming Language :: Python :: 3
Classifier: Environment :: Console
Requires-Python: >=3
